README.md
setup.py
canotic/__init__.py
canotic/cli.py
canotic/client.py
canotic/config.py
canotic/exceptions.py
canotic/apis/__init__.py
canotic/apis/auth.py
canotic/apis/data.py
canotic/apis/ground_truth.py
canotic/apis/jobs.py
canotic_api_client.egg-info/PKG-INFO
canotic_api_client.egg-info/SOURCES.txt
canotic_api_client.egg-info/dependency_links.txt
canotic_api_client.egg-info/entry_points.txt
canotic_api_client.egg-info/requires.txt
canotic_api_client.egg-info/top_level.txt