Metadata-Version: 1.0
Name: canotic-api-client
Version: 0.0.1
Summary: Canotic API
Home-page: https://canotic.com/
Author: UNKNOWN
Author-email: UNKNOWN
License: UNKNOWN
Keywords: Canotic API
Platform: UNKNOWN
